weathercli/__init__.py
wethr-0.0.1.data/scripts/weather
wethr-0.0.1.dist-info/LICENSE.txt
wethr-0.0.1.dist-info/METADATA
wethr-0.0.1.dist-info/WHEEL
wethr-0.0.1.dist-info/top_level.txt
wethr-0.0.1.dist-info/RECORD
