Metadata-Version: 2.1
Name: wethr
Version: 0.0.1
Summary: Weather.com CLI
Home-page: UNKNOWN
License: UNKNOWN
Platform: UNKNOWN
Requires-Python: >=3.6.3
Requires-Dist: geopy (==1.20.0)
Requires-Dist: requests (==2.21.0)
